nicehr/__init__.py
nicehr/__main__.py
nicehr/nicehr.py
nicehr-1.0.0.1.dist-info/LICENSE
nicehr-1.0.0.1.dist-info/METADATA
nicehr-1.0.0.1.dist-info/WHEEL
nicehr-1.0.0.1.dist-info/top_level.txt
nicehr-1.0.0.1.dist-info/RECORD
