Metadata-Version: 2.1
Name: nicehr
Version: 1.0.0.1
Summary: Nice Autoscaling Horizontal Rules for Python
Home-page: https://github.com/dagonis/nicehr
Author: Kevin Tyers
Author-email: ktyers+pypi@gmail.com
License: UNKNOWN
Platform: UNKNOWN
Classifier: Programming Language :: Python :: 3
Classifier: Programming Language :: Python :: 3.6
Classifier: Programming Language :: Python :: 3.7
Classifier: Programming Language :: Python :: 3.8
Classifier: License :: OSI Approved :: GNU General Public License v3 (GPLv3)
Classifier: Operating System :: OS Independent
Classifier: Natural Language :: English
Requires-Dist: colored
